obsidian_ai/__init__.py
obsidian_ai/local_embed.py
obsidian_ai/semsearch.py
obsidian_ai/core/__init__.py
obsidian_ai/core/research_agent.py
obsidian_ai/core/search_engine.py
obsidian_ai/core/wikilink_parser.py
obsidian_ai/infrastructure/__init__.py
obsidian_ai/infrastructure/config.py
obsidian_ai/infrastructure/file_system.py
obsidian_ai/interfaces/__init__.py
obsidian_ai/interfaces/chat.py
obsidian_ai/interfaces/cli.py
obsidian_ai/interfaces/tools.py
obsidian_ai/prompts/__init__.py
obsidian_ai/prompts/base.py
obsidian_ai/prompts/chat.py
obsidian_ai/prompts/research.py
obsidian_ai/services/__init__.py
obsidian_ai/services/embedding_service.py
obsidian_ai/services/openai_client.py
obsidian_ai-0.1.2.dist-info/METADATA
obsidian_ai-0.1.2.dist-info/WHEEL
obsidian_ai-0.1.2.dist-info/entry_points.txt
obsidian_ai-0.1.2.dist-info/licenses/LICENSE
obsidian_ai-0.1.2.dist-info/RECORD
