Metadata-Version: 2.4
Name: obsidian-ai
Version: 0.1.2
Summary: AI-powered semantic search and chat for Obsidian notes
Author-email: Sumuk Shashidhar <sumukuuu@gmail.com>
License-File: LICENSE
Requires-Python: >=3.12
Requires-Dist: click>=8.1
Requires-Dist: loguru>=0.7
Requires-Dist: numpy>=1.26
Requires-Dist: openai>=1.40.0
Requires-Dist: rich>=13.7
